uzi/__init__.py
uzi/_common/__init__.py
uzi/_common/lookups.py
uzi/_functools.py
uzi/_receivers.py
uzi/containers.py
uzi/exceptions.py
uzi/graph/__init__.py
uzi/graph/core.py
uzi/graph/nodes.py
uzi/injectors.py
uzi/markers.py
uzi/providers.py
uzi/scopes.py
uzi/signals.py
uzi-0.3.2.dist-info/LICENSE.txt
uzi-0.3.2.dist-info/WHEEL
uzi-0.3.2.dist-info/METADATA
uzi-0.3.2.dist-info/RECORD
