Metadata-Version: 2.1
Name: uzi
Version: 0.3.2
Summary: Dependency injection library
Home-page: https://github.com/pyuzi/uzi
License: MIT
Keywords: dependency-injection,inversion-of-control,inversion-of-control-container,IoC-Container,service-injector,injector,IoC,DI,Uzi
Author: David Kyalo
Author-email: davidmkyalo@gmail.com
Requires-Python: >=3.9,<4.0
Classifier: License :: OSI Approved :: MIT License
Classifier: Programming Language :: Python :: 3
Classifier: Programming Language :: Python :: 3.10
Classifier: Programming Language :: Python :: 3.9
Requires-Dist: attrs (>=21.4.0,<22.0.0)
Requires-Dist: blinker (>=1.4,<2.0)
Requires-Dist: typing-extensions (>=4.1.1,<5.0.0)
Project-URL: Documentation, https://pyuzi.github.io/uzi
Project-URL: Repository, https://github.com/pyuzi/uzi
